nmapvulners2csv/__init__.py
nmapvulners2csv/nmapvulners2csv.py
nmapvulners2csv-1.1.0.dist-info/METADATA
nmapvulners2csv-1.1.0.dist-info/WHEEL
nmapvulners2csv-1.1.0.dist-info/entry_points.txt
nmapvulners2csv-1.1.0.dist-info/licenses/LICENSE
nmapvulners2csv-1.1.0.dist-info/RECORD
