Metadata-Version: 2.4
Name: nmapvulners2csv
Version: 1.1.0
Summary: Convert Nmap Vulners script output to CSV
License: LICENSE
License-File: LICENSE
Author: SecSI
Author-email: dev@secsi.io
Requires-Python: >=3.8,<4.0
Classifier: License :: Other/Proprietary License
Classifier: Programming Language :: Python :: 3
Classifier: Programming Language :: Python :: 3.8
Classifier: Programming Language :: Python :: 3.9
Classifier: Programming Language :: Python :: 3.10
Classifier: Programming Language :: Python :: 3.11
Classifier: Programming Language :: Python :: 3.12
Classifier: Programming Language :: Python :: 3.13
Classifier: Programming Language :: Python :: 3.14
Requires-Dist: beautifulsoup4 (>=4.11.1,<5.0.0)
Requires-Dist: bs4 (>=0.0.1,<0.0.2)
Requires-Dist: elementpath (==4.1.5)
Requires-Dist: fire (==0.7.0)
Requires-Dist: requests (>=2.31.0,<3.0.0)
Requires-Dist: six (>=1.16.0,<2.0.0)
Requires-Dist: soupsieve (>=2.3.2.post1,<3.0.0)
Requires-Dist: termcolor (>=2.0.1,<3.0.0)
